  1           0 LOAD_CONST               0 (0)
              2 LOAD_CONST               1 (None)
              4 IMPORT_NAME              0 (winsound)
              6 STORE_NAME               0 (winsound)

  2           8 LOAD_CONST               0 (0)
             10 LOAD_CONST               2 (('sleep',))
             12 IMPORT_NAME              1 (time)
             14 IMPORT_FROM              2 (sleep)
             16 STORE_NAME               2 (sleep)
             18 POP_TOP

  3          20 LOAD_CONST               0 (0)
             22 LOAD_CONST               3 (('floor',))
             24 IMPORT_NAME              3 (math)
             26 IMPORT_FROM              4 (floor)
             28 STORE_NAME               4 (floor)
             30 POP_TOP

  5          32 LOAD_CONST               4 ('a')
             34 LOAD_CONST               5 (261.63)
             36 BUILD_MAP                1
             38 STORE_NAME               5 (keytone)

  6          40 LOAD_NAME                5 (keytone)
             42 LOAD_CONST               4 ('a')
             44 BINARY_SUBSCR
             46 STORE_NAME               6 (pt)

  7          48 LOAD_CONST               6 (('w', 's', 'e', 'd', 'f', 't', 'g', 'y', 'h', 'u', 'j', 'k', 'o', 'l', 'p', ';', "'", '[', ']', ' '))
             50 GET_ITER
        >>   52 FOR_ITER                30 (to 84)
             54 STORE_NAME               7 (k)

  8          56 LOAD_NAME                6 (pt)
             58 LOAD_NAME                8 (pow)
             60 LOAD_CONST               7 (2)
             62 LOAD_CONST               8 (0.08333333333333333)
             64 CALL_FUNCTION            2
             66 BINARY_MULTIPLY
             68 LOAD_NAME                5 (keytone)
             70 LOAD_NAME                7 (k)
             72 STORE_SUBSCR

  9          74 LOAD_NAME                5 (keytone)
             76 LOAD_NAME                7 (k)
             78 BINARY_SUBSCR
             80 STORE_NAME               6 (pt)
             82 JUMP_ABSOLUTE           52

 11     >>   84 LOAD_NAME                9 (print)
             86 LOAD_CONST               9 ('Play some music to please me, despicable outlander....')
             88 CALL_FUNCTION            1
             90 POP_TOP

 12          92 LOAD_NAME                9 (print)
             94 LOAD_CONST              10 ("\n ________________________________________________________\n|  | | | |  |  | | | | | |  |  | | | |  |  | | | | | |  |\n|  | | | |  |  | | | | | |  |  | | | |  |  | | | | | |  |\n|  |w| |e|  |  |t| |y| |u|  |  |o| |p|  |  |[| | | | |  |\n|  |_| |_|  |  |_| |_| |_|  |  |_| |_|  |  |_| |_| |_|  |\n|   |   |   |   |   |   |   |   |   |   |   |   |   |   |\n| a | s | d | f | g | h | j | k | l | ; | ' | ] |   |   |\n|___|___|___|___|___|___|___|___|___|___|___|___|___|___|\n")
             96 CALL_FUNCTION            1
             98 POP_TOP

 23         100 LOAD_NAME               10 (input)
            102 CALL_FUNCTION            0
            104 STORE_NAME              11 (notes)

 24         106 LOAD_CONST              11 ('-')
            108 LOAD_CONST              12 (1)
            110 BUILD_LIST               2
            112 BUILD_LIST               1
            114 STORE_NAME              12 (play)

 25         116 LOAD_NAME               11 (notes)
            118 GET_ITER
        >>  120 FOR_ITER                56 (to 178)
            122 STORE_NAME              13 (note)

 26         124 LOAD_NAME               13 (note)
            126 LOAD_NAME               12 (play)
            128 LOAD_CONST              13 (-1)
            130 BINARY_SUBSCR
            132 LOAD_CONST               0 (0)
            134 BINARY_SUBSCR
            136 COMPARE_OP               2 (==)
            138 POP_JUMP_IF_FALSE      162

 27         140 LOAD_NAME               12 (play)
            142 LOAD_CONST              13 (-1)
            144 BINARY_SUBSCR
            146 LOAD_CONST              12 (1)
            148 DUP_TOP_TWO
            150 BINARY_SUBSCR
            152 LOAD_CONST              12 (1)
            154 INPLACE_ADD
            156 ROT_THREE
            158 STORE_SUBSCR
            160 JUMP_FORWARD            14 (to 176)

 29     >>  162 LOAD_NAME               12 (play)
            164 LOAD_METHOD             14 (append)
            166 LOAD_NAME               13 (note)
            168 LOAD_CONST              12 (1)
            170 BUILD_LIST               2
            172 CALL_METHOD              1
            174 POP_TOP
        >>  176 JUMP_ABSOLUTE          120

 31     >>  178 LOAD_NAME               12 (play)
            180 GET_ITER
        >>  182 FOR_ITER                74 (to 258)
            184 STORE_NAME              13 (note)

 32         186 LOAD_NAME               13 (note)
            188 LOAD_CONST               0 (0)
            190 BINARY_SUBSCR
            192 LOAD_CONST              14 (' ')
            194 COMPARE_OP               2 (==)
            196 POP_JUMP_IF_FALSE      208

 33         198 LOAD_NAME                2 (sleep)
            200 LOAD_CONST              15 (0.2)
            202 CALL_FUNCTION            1
            204 POP_TOP
            206 JUMP_FORWARD            48 (to 256)

 34     >>  208 LOAD_NAME               13 (note)
            210 LOAD_CONST               0 (0)
            212 BINARY_SUBSCR
            214 LOAD_CONST              11 ('-')
            216 COMPARE_OP               2 (==)
            218 POP_JUMP_IF_FALSE      224

 35         220 JUMP_ABSOLUTE          182
            222 JUMP_FORWARD            32 (to 256)

 37     >>  224 LOAD_NAME                0 (winsound)
            226 LOAD_METHOD             15 (Beep)
            228 LOAD_NAME                4 (floor)
            230 LOAD_NAME                5 (keytone)
            232 LOAD_NAME               13 (note)
            234 LOAD_CONST               0 (0)
            236 BINARY_SUBSCR
            238 BINARY_SUBSCR
            240 CALL_FUNCTION            1
            242 LOAD_CONST              16 (200)
            244 LOAD_NAME               13 (note)
            246 LOAD_CONST              12 (1)
            248 BINARY_SUBSCR
            250 BINARY_MULTIPLY
            252 CALL_METHOD              2
            254 POP_TOP
        >>  256 JUMP_ABSOLUTE          182

 39     >>  258 BUILD_LIST               0
            260 STORE_NAME              16 (result)

 40         262 LOAD_NAME               17 (list)
            264 LOAD_NAME               18 (map)
            266 LOAD_NAME               19 (ord)
            268 LOAD_NAME               11 (notes)
            270 CALL_FUNCTION            2
            272 CALL_FUNCTION            1
            274 STORE_NAME              11 (notes)

 41         276 LOAD_NAME               20 (range)
            278 LOAD_NAME               21 (len)
            280 LOAD_NAME               11 (notes)
            282 CALL_FUNCTION            1
            284 LOAD_CONST              12 (1)
            286 BINARY_SUBTRACT
            288 CALL_FUNCTION            1
            290 GET_ITER
        >>  292 FOR_ITER                32 (to 326)
            294 STORE_NAME              22 (i)

 42         296 LOAD_NAME               16 (result)
            298 LOAD_METHOD             14 (append)
            300 LOAD_NAME               11 (notes)
            302 LOAD_NAME               22 (i)
            304 BINARY_SUBSCR
            306 LOAD_NAME               11 (notes)
            308 LOAD_NAME               22 (i)
            310 LOAD_CONST              12 (1)
            312 BINARY_ADD
            314 BINARY_SUBSCR
            316 BINARY_ADD
            318 CALL_METHOD              1
            320 POP_TOP
            322 EXTENDED_ARG             1
            324 JUMP_ABSOLUTE          292

 43     >>  326 LOAD_NAME               20 (range)
            328 LOAD_NAME               21 (len)
            330 LOAD_NAME               11 (notes)
            332 CALL_FUNCTION            1
            334 LOAD_CONST              12 (1)
            336 BINARY_SUBTRACT
            338 CALL_FUNCTION            1
            340 GET_ITER
        >>  342 FOR_ITER                32 (to 376)
            344 STORE_NAME              22 (i)

 44         346 LOAD_NAME               16 (result)
            348 LOAD_METHOD             14 (append)
            350 LOAD_NAME               11 (notes)
            352 LOAD_NAME               22 (i)
            354 BINARY_SUBSCR
            356 LOAD_NAME               11 (notes)
            358 LOAD_NAME               22 (i)
            360 LOAD_CONST              12 (1)
            362 BINARY_ADD
            364 BINARY_SUBSCR
            366 BINARY_SUBTRACT
            368 CALL_METHOD              1
            370 POP_TOP
            372 EXTENDED_ARG             1
            374 JUMP_ABSOLUTE          342

 46     >>  376 LOAD_CONST              17 (216)
            378 LOAD_CONST              18 (219)
            380 LOAD_CONST              19 (222)
            382 LOAD_CONST              18 (219)
            384 LOAD_CONST              17 (216)
            386 LOAD_CONST              18 (219)
            388 LOAD_CONST              19 (222)
            390 LOAD_CONST              18 (219)
            392 LOAD_CONST              17 (216)
            394 LOAD_CONST              18 (219)
            396 LOAD_CONST              19 (222)
            398 LOAD_CONST              20 (202)
            400 LOAD_CONST              21 (150)
            402 LOAD_CONST              22 (167)
            404 LOAD_CONST              18 (219)
            406 LOAD_CONST              18 (219)
            408 LOAD_CONST              17 (216)
            410 LOAD_CONST              18 (219)
            412 LOAD_CONST              19 (222)
            414 LOAD_CONST              18 (219)
            416 LOAD_CONST              17 (216)
            418 LOAD_CONST              18 (219)
            420 LOAD_CONST              19 (222)
            422 LOAD_CONST              18 (219)
            424 LOAD_CONST              17 (216)
            426 LOAD_CONST              18 (219)
            428 LOAD_CONST              19 (222)
            430 LOAD_CONST              20 (202)
            432 LOAD_CONST              21 (150)
            434 LOAD_CONST              22 (167)
            436 LOAD_CONST              18 (219)
            438 LOAD_CONST              18 (219)
            440 LOAD_CONST              17 (216)
            442 LOAD_CONST              18 (219)
            444 LOAD_CONST              19 (222)
            446 LOAD_CONST              18 (219)
            448 LOAD_CONST              17 (216)
            450 LOAD_CONST              18 (219)
            452 LOAD_CONST              19 (222)
            454 LOAD_CONST              18 (219)
            456 LOAD_CONST              17 (216)
            458 LOAD_CONST              18 (219)
            460 LOAD_CONST              19 (222)
            462 LOAD_CONST              20 (202)
            464 LOAD_CONST              21 (150)
            466 LOAD_CONST              22 (167)
            468 LOAD_CONST              18 (219)
            470 LOAD_CONST              18 (219)
            472 LOAD_CONST              17 (216)
            474 LOAD_CONST              18 (219)
            476 LOAD_CONST              19 (222)
            478 LOAD_CONST              23 (217)
            480 LOAD_CONST              24 (212)
            482 LOAD_CONST              25 (210)
            484 LOAD_CONST              26 (208)
            486 LOAD_CONST              25 (210)
            488 LOAD_CONST              24 (212)
            490 LOAD_CONST              25 (210)
            492 LOAD_CONST              26 (208)
            494 LOAD_CONST              27 (136)
            496 LOAD_CONST              28 (140)
            498 LOAD_CONST              17 (216)
            500 LOAD_CONST              18 (219)
            502 LOAD_CONST              19 (222)
            504 LOAD_CONST              18 (219)
            506 LOAD_CONST              17 (216)
            508 LOAD_CONST              18 (219)
            510 LOAD_CONST              19 (222)
            512 LOAD_CONST              18 (219)
            514 LOAD_CONST              17 (216)
            516 LOAD_CONST              18 (219)
            518 LOAD_CONST              19 (222)
            520 LOAD_CONST              20 (202)
            522 LOAD_CONST              21 (150)
            524 LOAD_CONST              22 (167)
            526 LOAD_CONST              18 (219)
            528 LOAD_CONST              18 (219)
            530 LOAD_CONST              17 (216)
            532 LOAD_CONST              18 (219)
            534 LOAD_CONST              19 (222)
            536 LOAD_CONST              18 (219)
            538 LOAD_CONST              17 (216)
            540 LOAD_CONST              18 (219)
            542 LOAD_CONST              19 (222)
            544 LOAD_CONST              18 (219)
            546 LOAD_CONST              17 (216)
            548 LOAD_CONST              18 (219)
            550 LOAD_CONST              19 (222)
            552 LOAD_CONST              23 (217)
            554 LOAD_CONST              23 (217)
            556 LOAD_CONST              18 (219)
            558 LOAD_CONST              22 (167)
            560 LOAD_CONST              21 (150)
            562 LOAD_CONST              29 (182)
            564 LOAD_CONST              30 (199)
            566 LOAD_CONST              17 (216)
            568 LOAD_CONST              18 (219)
            570 LOAD_CONST              19 (222)
            572 LOAD_CONST              18 (219)
            574 LOAD_CONST              17 (216)
            576 LOAD_CONST              24 (212)
            578 LOAD_CONST              26 (208)
            580 LOAD_CONST              26 (208)
            582 LOAD_CONST              26 (208)
            584 LOAD_CONST              31 (149)
            586 LOAD_CONST              31 (149)
            588 LOAD_CONST              25 (210)
            590 LOAD_CONST              23 (217)
            592 LOAD_CONST              18 (219)
            594 LOAD_CONST              22 (167)
            596 LOAD_CONST              21 (150)
            598 LOAD_CONST              29 (182)
            600 LOAD_CONST              30 (199)
            602 LOAD_CONST              17 (216)
            604 LOAD_CONST              18 (219)
            606 LOAD_CONST              19 (222)
            608 LOAD_CONST              18 (219)
            610 LOAD_CONST              17 (216)
            612 LOAD_CONST              32 (211)
            614 LOAD_CONST              33 (206)
            616 LOAD_CONST               0 (0)
            618 LOAD_CONST              34 (-3)
            620 LOAD_CONST               0 (0)
            622 LOAD_CONST              35 (3)
            624 LOAD_CONST               0 (0)
            626 LOAD_CONST              34 (-3)
            628 LOAD_CONST               0 (0)
            630 LOAD_CONST              35 (3)
            632 LOAD_CONST               0 (0)
            634 LOAD_CONST              34 (-3)
            636 LOAD_CONST               0 (0)
            638 LOAD_CONST              36 (20)
            640 LOAD_CONST              37 (32)
            642 LOAD_CONST              38 (-49)
            644 LOAD_CONST              34 (-3)
            646 LOAD_CONST              35 (3)
            648 LOAD_CONST               0 (0)
            650 LOAD_CONST              34 (-3)
            652 LOAD_CONST               0 (0)
            654 LOAD_CONST              35 (3)
            656 LOAD_CONST               0 (0)
            658 LOAD_CONST              34 (-3)
            660 LOAD_CONST               0 (0)
            662 LOAD_CONST              35 (3)
            664 LOAD_CONST               0 (0)
            666 LOAD_CONST              34 (-3)
            668 LOAD_CONST               0 (0)
            670 LOAD_CONST              36 (20)
            672 LOAD_CONST              37 (32)
            674 LOAD_CONST              38 (-49)
            676 LOAD_CONST              34 (-3)
            678 LOAD_CONST              35 (3)
            680 LOAD_CONST               0 (0)
            682 LOAD_CONST              34 (-3)
            684 LOAD_CONST               0 (0)
            686 LOAD_CONST              35 (3)
            688 LOAD_CONST               0 (0)
            690 LOAD_CONST              34 (-3)
            692 LOAD_CONST               0 (0)
            694 LOAD_CONST              35 (3)
            696 LOAD_CONST               0 (0)
            698 LOAD_CONST              34 (-3)
            700 LOAD_CONST               0 (0)
            702 LOAD_CONST              36 (20)
            704 LOAD_CONST              37 (32)
            706 LOAD_CONST              38 (-49)
            708 LOAD_CONST              34 (-3)
            710 LOAD_CONST              35 (3)
            712 LOAD_CONST               0 (0)
            714 LOAD_CONST              34 (-3)
            716 LOAD_CONST               0 (0)
            718 LOAD_CONST              39 (5)
            720 LOAD_CONST               0 (0)
            722 LOAD_CONST               7 (2)
            724 LOAD_CONST               0 (0)
            726 LOAD_CONST              40 (-2)
            728 LOAD_CONST               0 (0)
            730 LOAD_CONST               7 (2)
            732 LOAD_CONST               0 (0)
            734 LOAD_CONST              41 (72)
            736 LOAD_CONST              42 (-76)
            738 LOAD_CONST               0 (0)
            740 LOAD_CONST              34 (-3)
            742 LOAD_CONST               0 (0)
            744 LOAD_CONST              35 (3)
            746 LOAD_CONST               0 (0)
            748 LOAD_CONST              34 (-3)
            750 LOAD_CONST               0 (0)
            752 LOAD_CONST              35 (3)
            754 LOAD_CONST               0 (0)
            756 LOAD_CONST              34 (-3)
            758 LOAD_CONST               0 (0)
            760 LOAD_CONST              36 (20)
            762 LOAD_CONST              37 (32)
            764 LOAD_CONST              38 (-49)
            766 LOAD_CONST              34 (-3)
            768 LOAD_CONST              35 (3)
            770 LOAD_CONST               0 (0)
            772 LOAD_CONST              34 (-3)
            774 LOAD_CONST               0 (0)
            776 LOAD_CONST              35 (3)
            778 LOAD_CONST               0 (0)
            780 LOAD_CONST              34 (-3)
            782 LOAD_CONST               0 (0)
            784 LOAD_CONST              35 (3)
            786 LOAD_CONST               0 (0)
            788 LOAD_CONST              34 (-3)
            790 LOAD_CONST               0 (0)
            792 LOAD_CONST              39 (5)
            794 LOAD_CONST              43 (-5)
            796 LOAD_CONST              35 (3)
            798 LOAD_CONST              44 (49)
            800 LOAD_CONST              45 (-32)
            802 LOAD_CONST               0 (0)
            804 LOAD_CONST              46 (-17)
            806 LOAD_CONST               0 (0)
            808 LOAD_CONST              34 (-3)
            810 LOAD_CONST               0 (0)
            812 LOAD_CONST              35 (3)
            814 LOAD_CONST               0 (0)
            816 LOAD_CONST              47 (4)
            818 LOAD_CONST               0 (0)
            820 LOAD_CONST               0 (0)
            822 LOAD_CONST               0 (0)
            824 LOAD_CONST              48 (59)
            826 LOAD_CONST              49 (-59)
            828 LOAD_CONST              40 (-2)
            830 LOAD_CONST              43 (-5)
            832 LOAD_CONST              35 (3)
            834 LOAD_CONST              44 (49)
            836 LOAD_CONST              45 (-32)
            838 LOAD_CONST               0 (0)
            840 LOAD_CONST              46 (-17)
            842 LOAD_CONST               0 (0)
            844 LOAD_CONST              34 (-3)
            846 LOAD_CONST               0 (0)
            848 LOAD_CONST              35 (3)
            850 LOAD_CONST               0 (0)
            852 LOAD_CONST              39 (5)
            854 LOAD_CONST               0 (0)
            856 BUILD_LIST             240
            858 STORE_NAME              23 (constraint)

 48         860 LOAD_NAME               16 (result)
            862 LOAD_NAME               23 (constraint)
            864 COMPARE_OP               2 (==)
            866 EXTENDED_ARG             5
            868 POP_JUMP_IF_FALSE     1440

 49         870 LOAD_CONST              50 (62)
            872 LOAD_CONST              51 (9)
            874 LOAD_CONST              52 (11)
            876 LOAD_CONST              53 (79)
            878 LOAD_CONST               0 (0)
            880 LOAD_CONST              39 (5)
            882 LOAD_CONST              47 (4)
            884 LOAD_CONST              54 (10)
            886 LOAD_CONST              55 (76)
            888 LOAD_CONST              56 (30)
            890 LOAD_CONST               0 (0)
            892 LOAD_CONST              57 (28)
            894 LOAD_CONST              50 (62)
            896 LOAD_CONST              41 (72)
            898 LOAD_CONST              55 (76)
            900 LOAD_CONST              51 (9)
            902 LOAD_CONST              39 (5)
            904 LOAD_CONST               0 (0)
            906 LOAD_CONST              35 (3)
            908 LOAD_CONST              57 (28)
            910 LOAD_CONST              55 (76)
            912 LOAD_CONST              12 (1)
            914 LOAD_CONST              58 (22)
            916 LOAD_CONST              53 (79)
            918 LOAD_CONST              59 (8)
            920 LOAD_CONST              56 (30)
            922 LOAD_CONST              54 (10)
            924 LOAD_CONST              60 (14)
            926 LOAD_CONST              61 (54)
            928 LOAD_CONST              41 (72)
            930 LOAD_CONST              62 (102)
            932 LOAD_CONST              63 (46)
            934 LOAD_CONST               7 (2)
            936 LOAD_CONST              59 (8)
            938 LOAD_CONST              53 (79)
            940 LOAD_CONST              64 (13)
            942 LOAD_CONST              56 (30)
            944 LOAD_CONST              39 (5)
            946 LOAD_CONST              12 (1)
            948 LOAD_CONST              59 (8)
            950 LOAD_CONST              65 (31)
            952 LOAD_CONST              55 (76)
            954 LOAD_CONST               7 (2)
            956 LOAD_CONST              54 (10)
            958 LOAD_CONST              66 (123)
            960 LOAD_CONST              53 (79)
            962 LOAD_CONST              35 (3)
            964 LOAD_CONST              53 (79)
            966 LOAD_CONST              67 (24)
            968 LOAD_CONST              47 (4)
            970 LOAD_CONST              54 (10)
            972 LOAD_CONST              53 (79)
            974 LOAD_CONST              68 (26)
            976 LOAD_CONST              69 (6)
            978 LOAD_CONST              51 (9)
            980 LOAD_CONST              52 (11)
            982 LOAD_CONST              70 (15)
            984 LOAD_CONST              71 (74)
            986 LOAD_CONST              72 (17)
            988 LOAD_CONST              73 (7)
            990 LOAD_CONST              74 (85)
            992 LOAD_CONST              55 (76)
            994 LOAD_CONST              56 (30)
            996 LOAD_CONST              54 (10)
            998 LOAD_CONST              57 (28)
           1000 LOAD_CONST              67 (24)
           1002 LOAD_CONST              62 (102)
           1004 LOAD_CONST              75 (56)
           1006 LOAD_CONST              73 (7)
           1008 LOAD_CONST              39 (5)
           1010 LOAD_CONST              67 (24)
           1012 LOAD_CONST              54 (10)
           1014 LOAD_CONST              53 (79)
           1016 LOAD_CONST              76 (50)
           1018 LOAD_CONST              41 (72)
           1020 LOAD_CONST              55 (76)
           1022 LOAD_CONST              77 (12)
           1024 LOAD_CONST              35 (3)
           1026 LOAD_CONST               0 (0)
           1028 LOAD_CONST              52 (11)
           1030 LOAD_CONST              53 (79)
           1032 LOAD_CONST              64 (13)
           1034 LOAD_CONST               7 (2)
           1036 LOAD_CONST              52 (11)
           1038 LOAD_CONST              53 (79)
           1040 LOAD_CONST              64 (13)
           1042 LOAD_CONST               0 (0)
           1044 LOAD_CONST              67 (24)
           1046 LOAD_CONST              60 (14)
           1048 LOAD_CONST              78 (19)
           1050 LOAD_CONST              57 (28)
           1052 LOAD_CONST              55 (76)
           1054 LOAD_CONST              79 (66)
           1056 LOAD_CONST              50 (62)
           1058 LOAD_CONST              80 (58)
           1060 LOAD_CONST              56 (30)
           1062 LOAD_CONST               7 (2)
           1064 LOAD_CONST              69 (6)
           1066 LOAD_CONST              12 (1)
           1068 LOAD_CONST              52 (11)
           1070 LOAD_CONST              62 (102)
           1072 LOAD_CONST              81 (42)
           1074 LOAD_CONST              82 (29)
           1076 LOAD_CONST              68 (26)
           1078 LOAD_CONST              77 (12)
           1080 LOAD_CONST              41 (72)
           1082 LOAD_CONST              69 (6)
           1084 LOAD_CONST              70 (15)
           1086 LOAD_CONST              52 (11)
           1088 LOAD_CONST              55 (76)
           1090 LOAD_CONST              83 (89)
           1092 LOAD_CONST              84 (34)
           1094 LOAD_CONST              66 (123)
           1096 LOAD_CONST              64 (13)
           1098 LOAD_CONST              55 (76)
           1100 LOAD_CONST              82 (29)
           1102 LOAD_CONST               0 (0)
           1104 LOAD_CONST              85 (21)
           1106 LOAD_CONST              64 (13)
           1108 LOAD_CONST              52 (11)
           1110 LOAD_CONST              86 (71)
           1112 LOAD_CONST              67 (24)
           1114 LOAD_CONST              51 (9)
           1116 LOAD_CONST              57 (28)
           1118 LOAD_CONST              87 (27)
           1120 LOAD_CONST              62 (102)
           1122 LOAD_CONST              63 (46)
           1124 LOAD_CONST              35 (3)
           1126 LOAD_CONST              60 (14)
           1128 LOAD_CONST              70 (15)
           1130 LOAD_CONST              73 (7)
           1132 LOAD_CONST              53 (79)
           1134 LOAD_CONST              87 (27)
           1136 LOAD_CONST              88 (51)
           1138 LOAD_CONST              89 (94)
           1140 LOAD_CONST              55 (76)
           1142 LOAD_CONST              64 (13)
           1144 LOAD_CONST              51 (9)
           1146 LOAD_CONST              64 (13)
           1148 LOAD_CONST              57 (28)
           1150 LOAD_CONST              87 (27)
           1152 LOAD_CONST              55 (76)
           1154 LOAD_CONST              59 (8)
           1156 LOAD_CONST              54 (10)
           1158 LOAD_CONST              57 (28)
           1160 LOAD_CONST              70 (15)
           1162 LOAD_CONST              51 (9)
           1164 LOAD_CONST              12 (1)
           1166 LOAD_CONST              52 (11)
           1168 LOAD_CONST              90 (40)
           1170 LOAD_CONST              87 (27)
           1172 LOAD_CONST              54 (10)
           1174 LOAD_CONST              82 (29)
           1176 LOAD_CONST              35 (3)
           1178 LOAD_CONST              12 (1)
           1180 LOAD_CONST              53 (79)
           1182 LOAD_CONST              57 (28)
           1184 LOAD_CONST              47 (4)
           1186 LOAD_CONST              64 (13)
           1188 LOAD_CONST              52 (11)
           1190 LOAD_CONST               0 (0)
           1192 LOAD_CONST              87 (27)
           1194 LOAD_CONST              65 (31)
           1196 LOAD_CONST              91 (101)
           1198 LOAD_CONST              61 (54)
           1200 LOAD_CONST              50 (62)
           1202 LOAD_CONST              92 (87)
           1204 LOAD_CONST               0 (0)
           1206 LOAD_CONST               0 (0)
           1208 LOAD_CONST              87 (27)
           1210 LOAD_CONST              55 (76)
           1212 LOAD_CONST              64 (13)
           1214 LOAD_CONST              54 (10)
           1216 LOAD_CONST              52 (11)
           1218 LOAD_CONST              65 (31)
           1220 LOAD_CONST              57 (28)
           1222 LOAD_CONST              72 (17)
           1224 LOAD_CONST              71 (74)
           1226 LOAD_CONST              59 (8)
           1228 LOAD_CONST              82 (29)
           1230 LOAD_CONST              68 (26)
           1232 LOAD_CONST              93 (78)
           1234 LOAD_CONST              65 (31)
           1236 LOAD_CONST              62 (102)
           1238 LOAD_CONST              90 (40)
           1240 LOAD_CONST               0 (0)
           1242 LOAD_CONST               0 (0)
           1244 LOAD_CONST              59 (8)
           1246 LOAD_CONST              91 (101)
           1248 LOAD_CONST              60 (14)
           1250 LOAD_CONST               7 (2)
           1252 LOAD_CONST              59 (8)
           1254 LOAD_CONST              53 (79)
           1256 LOAD_CONST              94 (45)
           1258 LOAD_CONST              70 (15)
           1260 LOAD_CONST              95 (108)
           1262 LOAD_CONST              55 (76)
           1264 LOAD_CONST              51 (9)
           1266 LOAD_CONST              55 (76)
           1268 LOAD_CONST               0 (0)
           1270 LOAD_CONST              53 (79)
           1272 LOAD_CONST              60 (14)
           1274 LOAD_CONST              55 (76)
           1276 LOAD_CONST              52 (11)
           1278 LOAD_CONST              53 (79)
           1280 LOAD_CONST              69 (6)
           1282 LOAD_CONST              55 (76)
           1284 LOAD_CONST              65 (31)
           1286 LOAD_CONST              53 (79)
           1288 LOAD_CONST              63 (46)
           1290 LOAD_CONST              71 (74)
           1292 LOAD_CONST              96 (38)
           1294 LOAD_CONST              55 (76)
           1296 LOAD_CONST              97 (104)
           1298 LOAD_CONST              66 (123)
           1300 LOAD_CONST              97 (104)
           1302 LOAD_CONST              55 (76)
           1304 LOAD_CONST              98 (23)
           1306 LOAD_CONST              87 (27)
           1308 LOAD_CONST              73 (7)
           1310 LOAD_CONST              99 (93)
           1312 LOAD_CONST              65 (31)
           1314 LOAD_CONST             100 (55)
           1316 LOAD_CONST              60 (14)
           1318 LOAD_CONST              47 (4)
           1320 LOAD_CONST             101 (92)
           1322 LOAD_CONST              71 (74)
           1324 LOAD_CONST             100 (55)
           1326 LOAD_CONST              67 (24)
           1328 LOAD_CONST              54 (10)
           1330 LOAD_CONST              59 (8)
           1332 LOAD_CONST             102 (100)
           1334 LOAD_CONST             100 (55)
           1336 LOAD_CONST              76 (50)
           1338 LOAD_CONST              73 (7)
           1340 LOAD_CONST             103 (95)
           1342 LOAD_CONST             104 (48)
           1344 LOAD_CONST              82 (29)
           1346 LOAD_CONST              35 (3)
           1348 LOAD_CONST              65 (31)
           1350 LOAD_CONST             105 (84)
           1352 LOAD_CONST              36 (20)
           1354 LOAD_CONST              88 (51)
           1356 LOAD_CONST              54 (10)
           1358 LOAD_CONST              89 (94)
           1360 LOAD_CONST              35 (3)
           1362 LOAD_CONST               0 (0)
           1364 LOAD_CONST              65 (31)
           1366 LOAD_CONST             104 (48)
           1368 LOAD_CONST              87 (27)
           1370 LOAD_CONST              64 (13)
           1372 LOAD_CONST              99 (93)
           1374 LOAD_CONST              67 (24)
           1376 LOAD_CONST              60 (14)
           1378 LOAD_CONST             106 (53)
           1380 LOAD_CONST             107 (70)
           1382 EXTENDED_ARG             1
           1384 BUILD_LIST             256
           1386 STORE_NAME              24 (secret)

 50        1388 LOAD_CONST             108 ('')
           1390 LOAD_METHOD             25 (join)
           1392 LOAD_NAME               18 (map)
           1394 LOAD_NAME               26 (chr)
           1396 LOAD_CONST             109 (<code object <listcomp> at 0x7f91f4bc6b30, file "rose.py", line 50>)
           1398 LOAD_CONST             110 ('<listcomp>')
           1400 MAKE_FUNCTION            0
           1402 LOAD_NAME               20 (range)
           1404 LOAD_NAME               21 (len)
           1406 LOAD_NAME               24 (secret)
           1408 CALL_FUNCTION            1
           1410 CALL_FUNCTION            1
           1412 GET_ITER
           1414 CALL_FUNCTION            1
           1416 CALL_FUNCTION            2
           1418 CALL_METHOD              1
           1420 STORE_NAME              27 (flag)

 51        1422 LOAD_NAME                9 (print)
           1424 LOAD_CONST             111 ('That sounds good... I like to write the lyric for it')
           1426 CALL_FUNCTION            1
           1428 POP_TOP

 52        1430 LOAD_NAME                9 (print)
           1432 LOAD_NAME               27 (flag)
           1434 CALL_FUNCTION            1
           1436 POP_TOP
           1438 JUMP_FORWARD             8 (to 1448)

 54     >> 1440 LOAD_NAME                9 (print)
           1442 LOAD_CONST             112 ('I said music, that sounds like diarrhea')
           1444 CALL_FUNCTION            1
           1446 POP_TOP

 56     >> 1448 LOAD_NAME               10 (input)
           1450 CALL_FUNCTION            0
           1452 POP_TOP
           1454 LOAD_CONST               1 (None)
           1456 RETURN_VALUE

Disassembly of <code object <listcomp> at 0x7f91f4bc6b30, file "rose.py", line 50>:
 50           0 BUILD_LIST               0
              2 LOAD_FAST                0 (.0)
        >>    4 FOR_ITER                28 (to 34)
              6 STORE_FAST               1 (i)
              8 LOAD_GLOBAL              0 (secret)
             10 LOAD_FAST                1 (i)
             12 BINARY_SUBSCR
             14 LOAD_GLOBAL              1 (notes)
             16 LOAD_FAST                1 (i)
             18 LOAD_GLOBAL              2 (len)
             20 LOAD_GLOBAL              1 (notes)
             22 CALL_FUNCTION            1
             24 BINARY_MODULO
             26 BINARY_SUBSCR
             28 BINARY_XOR
             30 LIST_APPEND              2
             32 JUMP_ABSOLUTE            4
        >>   34 RETURN_VALUE
